LICENSE.txt
MANIFEST.in
README.md
setup.cfg
setup.py
configen/__init__.py
configen/admin.py
configen/apps.py
configen/config_processors.py
configen/models.py
configen/tests.py
configen/views.py
configen/management/__init__.py
configen/management/commands/__init__.py
configen/management/commands/configen.py
configen/migrations/__init__.py
django_configen.egg-info/PKG-INFO
django_configen.egg-info/SOURCES.txt
django_configen.egg-info/dependency_links.txt
django_configen.egg-info/not-zip-safe
django_configen.egg-info/requires.txt
django_configen.egg-info/top_level.txt